qcircpy/__init__.py
qcircpy/circuits.py
qcircpy/debugging.py
qcircpy/engine.py
qcircpy/exceptions.py
qcircpy/gates.py
qcircpy/quantum.py
qcircpy-0.2.2.dist-info/LICENSE
qcircpy-0.2.2.dist-info/METADATA
qcircpy-0.2.2.dist-info/WHEEL
qcircpy-0.2.2.dist-info/top_level.txt
qcircpy-0.2.2.dist-info/RECORD
