Metadata-Version: 2.1
Name: qcircpy
Version: 0.2.2
Summary: A package for Python Quantum Circuit Simulation and Benchmarking
Author-email: Jake Lu <jylu1205@outlook.com>
License: BSD 2-Clause License
Project-URL: Homepage, https://github.com/Deftioon/qcircpy
Project-URL: Issues, https://github.com/Deftioon/qcircpy/issues
Keywords: quantum,circuit,simulation,benchmarking
Classifier: Development Status :: 4 - Beta
Classifier: Programming Language :: Python :: 3.11
Classifier: License :: OSI Approved :: BSD License
Classifier: Operating System :: OS Independent
Classifier: Environment :: GPU :: NVIDIA CUDA :: 11
Classifier: Environment :: GPU :: NVIDIA CUDA :: 12
Classifier: Natural Language :: English
Requires-Python: >=3.11
License-File: LICENSE
Requires-Dist: numpy
